DomEnlightenment/README.md
DomEnlightenment/__init__.py
DomEnlightenment/__main__.py
DomEnlightenment/file.epub
DomEnlightenment/index.html
DomEnlightenment/css/__init__.py
DomEnlightenment/css/annotations.css
DomEnlightenment/css/main.css
DomEnlightenment/css/normalize.css
DomEnlightenment/css/popup.css
DomEnlightenment/font/__init__.py
DomEnlightenment/font/fontello.eot
DomEnlightenment/font/fontello.svg
DomEnlightenment/font/fontello.ttf
DomEnlightenment/font/fontello.woff
DomEnlightenment/img/__init__.py
DomEnlightenment/img/annotator-glyph-sprite.png
DomEnlightenment/img/annotator-icon-sprite.png
DomEnlightenment/img/apple-touch-icon.png
DomEnlightenment/img/cancelfullscreen.png
DomEnlightenment/img/close.png
DomEnlightenment/img/fullscreen.png
DomEnlightenment/img/loader.gif
DomEnlightenment/img/menu-icon.png
DomEnlightenment/img/save.png
DomEnlightenment/img/saved.png
DomEnlightenment/img/settings-s.png
DomEnlightenment/img/settings.png
DomEnlightenment/img/star.png
DomEnlightenment/js/__init__.py
DomEnlightenment/js/epub.js
DomEnlightenment/js/epub.min.js
DomEnlightenment/js/epub.min.map
DomEnlightenment/js/hooks.min.js
DomEnlightenment/js/hooks.min.map
DomEnlightenment/js/reader.js
DomEnlightenment/js/reader.js.map
DomEnlightenment/js/reader.min.js
DomEnlightenment/js/reader.min.map
DomEnlightenment/js/hooks/__init__.py
DomEnlightenment/js/hooks/extensions/__init__.py
DomEnlightenment/js/hooks/extensions/highlight.js
DomEnlightenment/js/libs/__init__.py
DomEnlightenment/js/libs/jquery.min.js
DomEnlightenment/js/libs/localforage.min.js
DomEnlightenment/js/libs/screenfull.js
DomEnlightenment/js/libs/screenfull.min.js
DomEnlightenment/js/libs/zip.min.js
DomEnlightenment/js/plugins/__init__.py
DomEnlightenment/js/plugins/hypothesis.js
DomEnlightenment/js/plugins/search.js
dom_enlightenment-2024.3.2.0.dist-info/METADATA
dom_enlightenment-2024.3.2.0.dist-info/WHEEL
dom_enlightenment-2024.3.2.0.dist-info/entry_points.txt
dom_enlightenment-2024.3.2.0.dist-info/top_level.txt
dom_enlightenment-2024.3.2.0.dist-info/RECORD
